{
  "markets": {
    "alembics": {
      "price": 0,
      "volume": 0,
      "volume_prev_12": 0
    },
    "arms": {
      "price": 20.751,
      "open_price": 20.408,
      "last_price": 20.751,
      "moving_average": 19.278,
      "highest_bid": 20.408,
      "lowest_ask": 21.788,
      "high_price": 20.408,
      "low_price": 20.408,
      "volume": 0,
      "volume_prev_12": 14,
      "bid_volume_10": 2,
      "ask_volume_10": 1
    },
    "axes": {
      "price": 15.098,
      "open_price": 42.285,
      "last_price": 15.098,
      "moving_average": 15.098,
      "lowest_ask": 42.285,
      "high_price": 42.285,
      "low_price": 42.285,
      "volume": 0,
      "volume_prev_12": 0,
      "ask_volume_10": 2
    },
    "beer": {
      "price": 3.666,
      "open_price": 3.666,
      "last_price": 3.666,
      "average_price": 3.666,
      "moving_average": 3.781,
      "lowest_ask": 3.666,
      "high_price": 3.666,
      "low_price": 3.666,
      "volume": 26,
      "volume_prev_12": 318,
      "ask_volume_10": 3
    },
    "belts": {
      "price": 2.028,
      "open_price": 2.028,
      "last_price": 2.028,
      "average_price": 2.028,
      "moving_average": 3.109,
      "lowest_ask": 4.569,
      "high_price": 2.028,
      "low_price": 2.028,
      "volume": 1,
      "volume_prev_12": 6,
      "ask_volume_10": 3
    },
    "blades": {
      "price": 20.008,
      "open_price": 12.642,
      "last_price": 20.008,
      "moving_average": 20.008,
      "highest_bid": 12.642,
      "lowest_ask": 15.08,
      "high_price": 12.642,
      "low_price": 12.642,
      "volume": 0,
      "volume_prev_12": 0,
      "bid_volume_10": 1,
      "ask_volume_10": 1
    },
    "bread": {
      "price": 2.834,
      "open_price": 2.834,
      "last_price": 2.834,
      "average_price": 2.834,
      "moving_average": 3.033,
      "lowest_ask": 2.834,
      "high_price": 2.834,
      "low_price": 2.834,
      "volume": 159,
      "volume_prev_12": 1764,
      "ask_volume_10": 6
    },
    "bricks": {
      "price": 6.728,
      "open_price": 6.728,
      "last_price": 6.728,
      "average_price": 6.728,
      "moving_average": 7.258,
      "lowest_ask": 6.728,
      "high_price": 6.728,
      "low_price": 6.728,
      "volume": 4,
      "volume_prev_12": 47,
      "ask_volume_10": 1
    },
    "butter": {
      "price": 82.823,
      "open_price": 196.881,
      "last_price": 82.823,
      "moving_average": 82.823,
      "lowest_ask": 196.881,
      "high_price": 196.881,
      "low_price": 196.881,
      "volume": 0,
      "volume_prev_12": 0,
      "ask_volume_10": 4
    },
    "candles": {
      "price": 60.006,
      "open_price": 101.643,
      "last_price": 60.006,
      "moving_average": 60.006,
      "lowest_ask": 101.643,
      "high_price": 101.643,
      "low_price": 101.643,
      "volume": 0,
      "volume_prev_12": 0,
      "ask_volume_10": 2
    },
    "carting": {
      "price": 0.744,
      "open_price": 0.744,
      "last_price": 0.744,
      "average_price": 0.744,
      "moving_average": 0.324,
      "highest_bid": 0.744,
      "lowest_ask": 0.9,
      "high_price": 0.744,
      "low_price": 0.744,
      "volume": 20,
      "volume_prev_12": 364,
      "bid_volume_10": 40,
      "ask_volume_10": 10000000
    },
    "casks": {
      "price": 3.921,
      "open_price": 3.921,
      "last_price": 3.921,
      "average_price": 3.921,
      "moving_average": 5.999,
      "lowest_ask": 3.921,
      "high_price": 3.921,
      "low_price": 3.921,
      "volume": 1,
      "volume_prev_12": 60,
      "ask_volume_10": 1
    },
    "cattle": {
      "price": 57.653,
      "open_price": 120.086,
      "last_price": 57.653,
      "moving_average": 57.653,
      "lowest_ask": 120.086,
      "high_price": 120.086,
      "low_price": 120.086,
      "volume": 0,
      "volume_prev_12": 0,
      "ask_volume_10": 2
    },
    "charcoal": {
      "price": 2.013,
      "open_price": 2.013,
      "last_price": 2.013,
      "average_price": 2.013,
      "moving_average": 1.677,
      "highest_bid": 1.99,
      "lowest_ask": 2.013,
      "high_price": 2.013,
      "low_price": 2.013,
      "volume": 24,
      "volume_prev_12": 264,
      "bid_volume_10": 1,
      "ask_volume_10": 1
    },
    "cheese": {
      "price": 5.636,
      "open_price": 5.636,
      "last_price": 5.636,
      "average_price": 5.636,
      "moving_average": 5.594,
      "highest_bid": 4.291,
      "lowest_ask": 5.721,
      "high_price": 5.636,
      "low_price": 5.636,
      "volume": 17,
      "volume_prev_12": 172,
      "bid_volume_10": 1,
      "ask_volume_10": 2
    },
    "clay": {
      "price": 6.188,
      "open_price": 6.188,
      "highest_bid": 6.188,
      "high_price": 6.188,
      "low_price": 6.188,
      "volume": 0,
      "volume_prev_12": 0,
      "bid_volume_10": 1
    },
    "cloth": {
      "price": 7.957,
      "open_price": 7.957,
      "last_price": 7.957,
      "average_price": 7.957,
      "moving_average": 8.132,
      "highest_bid": 6.194,
      "lowest_ask": 7.957,
      "high_price": 7.957,
      "low_price": 7.957,
      "volume": 27,
      "volume_prev_12": 369,
      "bid_volume_10": 3,
      "ask_volume_10": 16
    },
    "coats": {
      "price": 169.381,
      "open_price": 254.642,
      "last_price": 169.381,
      "moving_average": 169.381,
      "lowest_ask": 254.642,
      "high_price": 254.642,
      "low_price": 254.642,
      "volume": 0,
      "volume_prev_12": 0,
      "ask_volume_10": 2
    },
    "cookware": {
      "price": 19.325,
      "open_price": 19.325,
      "last_price": 19.325,
      "average_price": 19.325,
      "moving_average": 17.552,
      "highest_bid": 19.325,
      "lowest_ask": 19.77,
      "high_price": 19.325,
      "low_price": 19.325,
      "volume": 5,
      "volume_prev_12": 59,
      "bid_volume_10": 2,
      "ask_volume_10": 4
    },
    "copper ingots": {
      "price": 10.784,
      "open_price": 10.784,
      "last_price": 10.784,
      "average_price": 10.784,
      "moving_average": 11.17,
      "highest_bid": 10.48,
      "high_price": 10.784,
      "low_price": 10.784,
      "volume": 10,
      "volume_prev_12": 89,
      "bid_volume_10": 4
    },
    "copper ore": {
      "price": 16.314,
      "open_price": 16.314,
      "last_price": 16.314,
      "average_price": 16.314,
      "moving_average": 15.315,
      "highest_bid": 16.314,
      "high_price": 16.314,
      "low_price": 16.314,
      "volume": 4,
      "volume_prev_12": 48,
      "bid_volume_10": 1
    },
    "cured fish": {
      "price": 29.509,
      "open_price": 29.509,
      "last_price": 29.509,
      "average_price": 29.509,
      "moving_average": 27.068,
      "highest_bid": 28.281,
      "lowest_ask": 30.343,
      "high_price": 29.509,
      "low_price": 29.509,
      "volume": 4,
      "volume_prev_12": 75,
      "bid_volume_10": 4,
      "ask_volume_10": 3
    },
    "cured meat": {
      "price": 25.041,
      "open_price": 25.041,
      "last_price": 25.041,
      "average_price": 25.041,
      "moving_average": 22.63,
      "highest_bid": 23.725,
      "lowest_ask": 25.688,
      "high_price": 25.041,
      "low_price": 25.041,
      "volume": 3,
      "volume_prev_12": 47,
      "bid_volume_10": 5,
      "ask_volume_10": 5
    },
    "donations": {
      "price": 1,
      "open_price": 1,
      "last_price": 1,
      "moving_average": 1,
      "lowest_ask": 1,
      "high_price": 1,
      "low_price": 1,
      "volume": 0,
      "volume_prev_12": 0,
      "ask_volume_10": 100000
    },
    "dye": {
      "price": 38.328,
      "open_price": 159.278,
      "last_price": 38.328,
      "moving_average": 38.328,
      "lowest_ask": 159.278,
      "high_price": 159.278,
      "low_price": 159.278,
      "volume": 0,
      "volume_prev_12": 0,
      "ask_volume_10": 2
    },
    "dyed cloth": {
      "price": 18.225,
      "open_price": 18.225,
      "last_price": 18.225,
      "average_price": 18.225,
      "moving_average": 17.138,
      "highest_bid": 16.94,
      "lowest_ask": 18.462,
      "high_price": 18.225,
      "low_price": 18.225,
      "volume": 2,
      "volume_prev_12": 25,
      "bid_volume_10": 1,
      "ask_volume_10": 2
    },
    "firewood": {
      "price": 11.864,
      "open_price": 11.864,
      "last_price": 11.864,
      "average_price": 11.864,
      "moving_average": 11.75,
      "highest_bid": 11.089,
      "lowest_ask": 11.864,
      "high_price": 11.864,
      "low_price": 11.864,
      "volume": 42,
      "volume_prev_12": 417,
      "bid_volume_10": 3,
      "ask_volume_10": 10
    },
    "fish": {
      "price": 2.451,
      "last_price": 2.451,
      "moving_average": 2.451,
      "high_price": 2.451,
      "low_price": 2.451,
      "volume": 0,
      "volume_prev_12": 0
    },
    "flax fibres": {
      "price": 3.26,
      "open_price": 3.26,
      "last_price": 3.26,
      "average_price": 3.26,
      "moving_average": 3.416,
      "highest_bid": 3.225,
      "lowest_ask": 4.22,
      "high_price": 3.26,
      "low_price": 3.26,
      "volume": 11,
      "volume_prev_12": 109,
      "bid_volume_10": 4,
      "ask_volume_10": 1
    },
    "flax plants": {
      "price": 0.997,
      "open_price": 0.997,
      "last_price": 0.997,
      "average_price": 0.997,
      "moving_average": 1.166,
      "highest_bid": 0.967,
      "lowest_ask": 0.997,
      "high_price": 0.997,
      "low_price": 0.997,
      "volume": 17,
      "volume_prev_12": 200,
      "bid_volume_10": 1,
      "ask_volume_10": 3
    },
    "flour": {
      "price": 31.157,
      "open_price": 51.219,
      "last_price": 31.157,
      "moving_average": 31.157,
      "lowest_ask": 51.219,
      "high_price": 51.219,
      "low_price": 51.219,
      "volume": 0,
      "volume_prev_12": 0,
      "ask_volume_10": 2
    },
    "furniture": {
      "price": 15.392,
      "open_price": 15.392,
      "last_price": 15.392,
      "average_price": 15.392,
      "moving_average": 16.14,
      "lowest_ask": 15.392,
      "high_price": 15.392,
      "low_price": 15.392,
      "volume": 4,
      "volume_prev_12": 48,
      "ask_volume_10": 3
    },
    "garments": {
      "price": 22.213,
      "open_price": 22.213,
      "last_price": 22.213,
      "average_price": 22.213,
      "moving_average": 22.358,
      "highest_bid": 22.213,
      "high_price": 22.213,
      "low_price": 22.213,
      "volume": 17,
      "volume_prev_12": 204,
      "bid_volume_10": 9
    },
    "glass": {
      "price": 0,
      "volume": 0,
      "volume_prev_12": 0
    },
    "glassware": {
      "price": 57.385,
      "open_price": 127.32,
      "last_price": 57.385,
      "moving_average": 57.385,
      "lowest_ask": 127.32,
      "high_price": 127.32,
      "low_price": 127.32,
      "volume": 0,
      "volume_prev_12": 0,
      "ask_volume_10": 4
    },
    "gold bars": {
      "price": 1800,
      "open_price": 1615.68,
      "last_price": 1800,
      "moving_average": 1800,
      "highest_bid": 1615.68,
      "lowest_ask": 2056.319,
      "high_price": 1615.68,
      "low_price": 1615.68,
      "volume": 0,
      "volume_prev_12": 0,
      "bid_volume_10": 1,
      "ask_volume_10": 1
    },
    "gold ore": {
      "price": 329.28,
      "open_price": 424.404,
      "last_price": 329.28,
      "moving_average": 329.28,
      "lowest_ask": 424.404,
      "high_price": 424.404,
      "low_price": 424.404,
      "volume": 0,
      "volume_prev_12": 0,
      "ask_volume_10": 1
    },
    "grain": {
      "price": 3.124,
      "open_price": 3.124,
      "last_price": 3.124,
      "average_price": 3.124,
      "moving_average": 3.068,
      "highest_bid": 2.53,
      "lowest_ask": 3.124,
      "high_price": 3.124,
      "low_price": 3.124,
      "volume": 143,
      "volume_prev_12": 1440,
      "bid_volume_10": 4,
      "ask_volume_10": 91
    },
    "grindstones": {
      "price": 400,
      "open_price": 352.8,
      "last_price": 400,
      "moving_average": 400,
      "highest_bid": 352.8,
      "lowest_ask": 431.199,
      "high_price": 352.8,
      "low_price": 352.8,
      "volume": 0,
      "volume_prev_12": 2,
      "bid_volume_10": 1,
      "ask_volume_10": 2
    },
    "ham": {
      "price": 163.24,
      "open_price": 250.251,
      "last_price": 163.24,
      "moving_average": 163.24,
      "lowest_ask": 250.251,
      "high_price": 250.251,
      "low_price": 250.251,
      "volume": 0,
      "volume_prev_12": 0,
      "ask_volume_10": 2
    },
    "harnesses": {
      "price": 46.379,
      "open_price": 33.449,
      "last_price": 46.379,
      "moving_average": 45.937,
      "lowest_ask": 33.449,
      "high_price": 33.449,
      "low_price": 33.449,
      "volume": 0,
      "volume_prev_12": 9,
      "ask_volume_10": 1
    },
    "herbs": {
      "price": 18.278,
      "open_price": 66.905,
      "last_price": 18.278,
      "moving_average": 18.278,
      "lowest_ask": 66.905,
      "high_price": 66.905,
      "low_price": 66.905,
      "volume": 0,
      "volume_prev_12": 0,
      "ask_volume_10": 4
    },
    "hides": {
      "price": 10.373,
      "open_price": 16.98,
      "last_price": 10.373,
      "moving_average": 10.373,
      "lowest_ask": 16.98,
      "high_price": 16.98,
      "low_price": 16.98,
      "volume": 0,
      "volume_prev_12": 0,
      "ask_volume_10": 4
    },
    "honey": {
      "price": 3.19,
      "open_price": 25.024,
      "last_price": 3.19,
      "moving_average": 3.19,
      "lowest_ask": 25.024,
      "high_price": 25.024,
      "low_price": 25.024,
      "volume": 0,
      "volume_prev_12": 0,
      "ask_volume_10": 4
    },
    "hop beer": {
      "price": 12.784,
      "open_price": 10.164,
      "last_price": 12.784,
      "moving_average": 12.784,
      "lowest_ask": 10.164,
      "high_price": 10.164,
      "low_price": 10.164,
      "volume": 0,
      "volume_prev_12": 0,
      "ask_volume_10": 1
    },
    "iron ore": {
      "price": 4.638,
      "open_price": 4.638,
      "last_price": 4.638,
      "average_price": 4.638,
      "moving_average": 3.432,
      "highest_bid": 3.176,
      "high_price": 4.638,
      "low_price": 4.638,
      "volume": 16,
      "volume_prev_12": 158,
      "bid_volume_10": 3
    },
    "jewellery": {
      "price": 65.241,
      "open_price": 141.27,
      "last_price": 65.241,
      "moving_average": 65.241,
      "lowest_ask": 141.27,
      "high_price": 141.27,
      "low_price": 141.27,
      "volume": 0,
      "volume_prev_12": 0,
      "ask_volume_10": 4
    },
    "labour": {
      "price": 1.392,
      "open_price": 1.392,
      "last_price": 1.392,
      "average_price": 1.392,
      "moving_average": 1.427,
      "lowest_ask": 1.392,
      "high_price": 1.392,
      "low_price": 1.392,
      "volume": 1008,
      "volume_prev_12": 10957,
      "ask_volume_10": 28
    },
    "lead bars": {
      "price": 11.462,
      "open_price": 31.28,
      "last_price": 11.462,
      "moving_average": 11.462,
      "lowest_ask": 31.28,
      "high_price": 31.28,
      "low_price": 31.28,
      "volume": 0,
      "volume_prev_12": 0,
      "ask_volume_10": 4
    },
    "lead ore": {
      "price": 11.466,
      "open_price": 25.024,
      "last_price": 11.466,
      "moving_average": 11.466,
      "lowest_ask": 25.024,
      "high_price": 25.024,
      "low_price": 25.024,
      "volume": 0,
      "volume_prev_12": 0,
      "ask_volume_10": 2
    },
    "leather": {
      "price": 17.997,
      "open_price": 17.997,
      "last_price": 17.138,
      "moving_average": 14.598,
      "highest_bid": 17.997,
      "high_price": 17.997,
      "low_price": 17.997,
      "volume": 0,
      "volume_prev_12": 2,
      "bid_volume_10": 3
    },
    "light armor": {
      "price": 0,
      "volume": 0,
      "volume_prev_12": 0
    },
    "limestone": {
      "price": 23.852,
      "open_price": 23.531,
      "last_price": 23.852,
      "moving_average": 23.852,
      "highest_bid": 23.531,
      "lowest_ask": 28.759,
      "high_price": 23.531,
      "low_price": 23.531,
      "volume": 0,
      "volume_prev_12": 0,
      "bid_volume_10": 2,
      "ask_volume_10": 2
    },
    "lodging": {
      "price": 2.799,
      "open_price": 2.799,
      "last_price": 2.799,
      "average_price": 2.799,
      "moving_average": 2.895,
      "lowest_ask": 2.842,
      "high_price": 2.799,
      "low_price": 2.799,
      "volume": 13,
      "volume_prev_12": 156,
      "ask_volume_10": 12
    },
    "lumber": {
      "price": 4.47,
      "open_price": 4.47,
      "highest_bid": 4.47,
      "high_price": 4.47,
      "low_price": 4.47,
      "volume": 0,
      "volume_prev_12": 0,
      "bid_volume_10": 1
    },
    "malt": {
      "price": 6.559,
      "open_price": 14.345,
      "last_price": 6.559,
      "moving_average": 6.559,
      "lowest_ask": 14.345,
      "high_price": 14.345,
      "low_price": 14.345,
      "volume": 0,
      "volume_prev_12": 0,
      "ask_volume_10": 4
    },
    "manure": {
      "price": 1.968,
      "open_price": 1.968,
      "highest_bid": 1.968,
      "high_price": 1.968,
      "low_price": 1.968,
      "volume": 0,
      "volume_prev_12": 0,
      "bid_volume_10": 1
    },
    "meat": {
      "price": 2.012,
      "open_price": 2.012,
      "last_price": 2.012,
      "average_price": 2.012,
      "moving_average": 2.326,
      "lowest_ask": 2.012,
      "high_price": 2.012,
      "low_price": 2.012,
      "volume": 12,
      "volume_prev_12": 121,
      "ask_volume_10": 5
    },
    "medicine": {
      "price": 161.774,
      "open_price": 204.883,
      "last_price": 161.774,
      "moving_average": 161.774,
      "lowest_ask": 204.883,
      "high_price": 204.883,
      "low_price": 204.883,
      "volume": 0,
      "volume_prev_12": 0,
      "ask_volume_10": 2
    },
    "milk": {
      "price": 2.115,
      "last_price": 2.115,
      "moving_average": 2.115,
      "high_price": 2.115,
      "low_price": 2.115,
      "volume": 0,
      "volume_prev_12": 0
    },
    "mouldboards": {
      "price": 0,
      "volume": 0,
      "volume_prev_12": 0
    },
    "nails": {
      "price": 7.461,
      "open_price": 7.461,
      "last_price": 7.461,
      "average_price": 7.461,
      "moving_average": 6.221,
      "highest_bid": 7.273,
      "high_price": 7.461,
      "low_price": 7.461,
      "volume": 7,
      "volume_prev_12": 85,
      "bid_volume_10": 5
    },
    "nets": {
      "price": 28.076,
      "open_price": 28.076,
      "last_price": 28.076,
      "average_price": 28.076,
      "moving_average": 31.813,
      "highest_bid": 22.341,
      "lowest_ask": 28.076,
      "high_price": 28.076,
      "low_price": 28.076,
      "volume": 3,
      "volume_prev_12": 26,
      "bid_volume_10": 2,
      "ask_volume_10": 1
    },
    "ox power": {
      "price": 0,
      "volume": 0,
      "volume_prev_12": 0
    },
    "pasties": {
      "price": 18.799,
      "open_price": 31.623,
      "last_price": 18.799,
      "moving_average": 18.799,
      "lowest_ask": 31.623,
      "high_price": 31.623,
      "low_price": 31.623,
      "volume": 0,
      "volume_prev_12": 0,
      "ask_volume_10": 2
    },
    "pickaxes": {
      "price": 18.984,
      "open_price": 42.298,
      "last_price": 18.984,
      "moving_average": 18.984,
      "lowest_ask": 42.298,
      "high_price": 42.298,
      "low_price": 42.298,
      "volume": 0,
      "volume_prev_12": 0,
      "ask_volume_10": 2
    },
    "pies": {
      "price": 25.875,
      "open_price": 25.875,
      "last_price": 22.52,
      "moving_average": 22.52,
      "highest_bid": 25.875,
      "lowest_ask": 31.624,
      "high_price": 25.875,
      "low_price": 25.875,
      "volume": 0,
      "volume_prev_12": 0,
      "bid_volume_10": 2,
      "ask_volume_10": 2
    },
    "ploughs": {
      "price": 44.594,
      "open_price": 319.498,
      "last_price": 44.594,
      "moving_average": 44.594,
      "lowest_ask": 319.498,
      "high_price": 319.498,
      "low_price": 319.498,
      "volume": 0,
      "volume_prev_12": 0,
      "ask_volume_10": 2
    },
    "protection": {
      "price": 5.918,
      "open_price": 5.918,
      "last_price": 5.918,
      "average_price": 5.918,
      "moving_average": 5.985,
      "highest_bid": 5.91,
      "lowest_ask": 5.918,
      "high_price": 5.918,
      "low_price": 5.918,
      "volume": 2,
      "volume_prev_12": 42,
      "bid_volume_10": 10,
      "ask_volume_10": 2
    },
    "resin": {
      "price": 0,
      "volume": 0,
      "volume_prev_12": 0
    },
    "rope": {
      "price": 76.694,
      "open_price": 133.436,
      "last_price": 76.694,
      "moving_average": 76.694,
      "lowest_ask": 133.436,
      "high_price": 133.436,
      "low_price": 133.436,
      "volume": 0,
      "volume_prev_12": 0,
      "ask_volume_10": 4
    },
    "sails": {
      "price": 0,
      "volume": 0,
      "volume_prev_12": 0
    },
    "salt": {
      "price": 5,
      "open_price": 5,
      "last_price": 5,
      "average_price": 5,
      "moving_average": 4.785,
      "highest_bid": 5,
      "lowest_ask": 5.57,
      "high_price": 5,
      "low_price": 5,
      "volume": 2,
      "volume_prev_12": 63,
      "bid_volume_10": 4,
      "ask_volume_10": 1
    },
    "scythes": {
      "price": 79.027,
      "open_price": 79.027,
      "last_price": 52.042,
      "moving_average": 52.042,
      "highest_bid": 79.027,
      "lowest_ask": 109.131,
      "high_price": 79.027,
      "low_price": 79.027,
      "volume": 0,
      "volume_prev_12": 0,
      "bid_volume_10": 1,
      "ask_volume_10": 1
    },
    "silver bars": {
      "price": 0,
      "volume": 0,
      "volume_prev_12": 0
    },
    "slaked lime": {
      "price": 0,
      "volume": 0,
      "volume_prev_12": 0
    },
    "spirits": {
      "price": 0,
      "volume": 0,
      "volume_prev_12": 0
    },
    "steel ingots": {
      "price": 15.514,
      "open_price": 48.122,
      "last_price": 15.514,
      "moving_average": 15.514,
      "lowest_ask": 48.122,
      "high_price": 48.122,
      "low_price": 48.122,
      "volume": 0,
      "volume_prev_12": 0,
      "ask_volume_10": 2
    },
    "stockfish": {
      "price": 183.64,
      "open_price": 128.333,
      "last_price": 183.64,
      "moving_average": 183.64,
      "lowest_ask": 128.333,
      "high_price": 128.333,
      "low_price": 128.333,
      "volume": 0,
      "volume_prev_12": 0,
      "ask_volume_10": 1
    },
    "swords": {
      "price": 0,
      "volume": 0,
      "volume_prev_12": 0
    },
    "tar": {
      "price": 0,
      "volume": 0,
      "volume_prev_12": 0
    },
    "thread": {
      "price": 4.072,
      "open_price": 4.072,
      "last_price": 4.072,
      "average_price": 4.072,
      "moving_average": 3.919,
      "highest_bid": 3.992,
      "lowest_ask": 4.072,
      "high_price": 4.072,
      "low_price": 4.072,
      "volume": 24,
      "volume_prev_12": 350,
      "bid_volume_10": 2,
      "ask_volume_10": 4
    },
    "tiles": {
      "price": 12.102,
      "open_price": 12.102,
      "last_price": 10.524,
      "moving_average": 8.909,
      "highest_bid": 12.102,
      "high_price": 12.102,
      "low_price": 12.102,
      "volume": 0,
      "volume_prev_12": 2,
      "bid_volume_10": 1
    },
    "timber": {
      "price": 25,
      "open_price": 25,
      "last_price": 25,
      "average_price": 25,
      "moving_average": 22.007,
      "highest_bid": 25,
      "high_price": 25,
      "low_price": 25,
      "volume": 6,
      "volume_prev_12": 46,
      "bid_volume_10": 1
    },
    "tools": {
      "price": 4.209,
      "open_price": 4.209,
      "last_price": 4.209,
      "average_price": 4.209,
      "moving_average": 4.306,
      "highest_bid": 4.192,
      "lowest_ask": 4.209,
      "high_price": 4.209,
      "low_price": 4.209,
      "volume": 10,
      "volume_prev_12": 103,
      "bid_volume_10": 3,
      "ask_volume_10": 4
    },
    "wax": {
      "price": 48.877,
      "open_price": 76.345,
      "last_price": 48.877,
      "moving_average": 48.877,
      "lowest_ask": 76.345,
      "high_price": 76.345,
      "low_price": 76.345,
      "volume": 0,
      "volume_prev_12": 0,
      "ask_volume_10": 2
    },
    "wheels": {
      "price": 33.217,
      "open_price": 33.217,
      "last_price": 33.217,
      "average_price": 33.217,
      "moving_average": 24.093,
      "high_price": 33.217,
      "low_price": 33.217,
      "volume": 1,
      "volume_prev_12": 2
    },
    "windows": {
      "price": 851.188,
      "open_price": 1199.742,
      "last_price": 851.188,
      "moving_average": 851.188,
      "lowest_ask": 1199.742,
      "high_price": 1199.742,
      "low_price": 1199.742,
      "volume": 0,
      "volume_prev_12": 0,
      "ask_volume_10": 1
    },
    "wine": {
      "price": 6.73,
      "open_price": 6.73,
      "last_price": 6.73,
      "average_price": 6.73,
      "moving_average": 5.995,
      "highest_bid": 6.696,
      "lowest_ask": 6.73,
      "high_price": 6.73,
      "low_price": 6.73,
      "volume": 5,
      "volume_prev_12": 83,
      "bid_volume_10": 2,
      "ask_volume_10": 5
    },
    "wool": {
      "price": 7.838,
      "open_price": 7.838,
      "last_price": 7.838,
      "average_price": 7.838,
      "moving_average": 9.228,
      "highest_bid": 7.838,
      "lowest_ask": 7.905,
      "high_price": 7.838,
      "low_price": 7.838,
      "volume": 10,
      "volume_prev_12": 131,
      "bid_volume_10": 3,
      "ask_volume_10": 5
    },
    "wrought iron": {
      "price": 11.519,
      "open_price": 11.519,
      "last_price": 11.519,
      "average_price": 11.519,
      "moving_average": 10.808,
      "highest_bid": 11.519,
      "lowest_ask": 11.663,
      "high_price": 11.519,
      "low_price": 11.519,
      "volume": 8,
      "volume_prev_12": 154,
      "bid_volume_10": 21,
      "ask_volume_10": 8
    },
    "yarn": {
      "price": 6.523,
      "open_price": 6.523,
      "last_price": 6.523,
      "average_price": 6.523,
      "moving_average": 4.215,
      "highest_bid": 6.523,
      "high_price": 6.523,
      "low_price": 6.523,
      "volume": 13,
      "volume_prev_12": 192,
      "bid_volume_10": 1
    }
  },
  "_ts": 1718903407840346
}