{
  "markets": {
    "alembics": {
      "price": 0,
      "volume": 0,
      "volume_prev_12": 0
    },
    "arms": {
      "price": 21.62,
      "open_price": 86.159,
      "last_price": 21.62,
      "moving_average": 21.62,
      "lowest_ask": 86.159,
      "high_price": 86.159,
      "low_price": 86.159,
      "volume": 0,
      "volume_prev_12": 0,
      "ask_volume_10": 2
    },
    "axes": {
      "price": 25.308,
      "open_price": 38.942,
      "last_price": 25.308,
      "moving_average": 25.308,
      "lowest_ask": 38.942,
      "high_price": 38.942,
      "low_price": 38.942,
      "volume": 0,
      "volume_prev_12": 0,
      "ask_volume_10": 2
    },
    "beer": {
      "price": 3.272,
      "open_price": 3.272,
      "last_price": 3.272,
      "average_price": 3.272,
      "moving_average": 2.931,
      "highest_bid": 3.246,
      "lowest_ask": 3.272,
      "high_price": 3.272,
      "low_price": 3.272,
      "volume": 23,
      "volume_prev_12": 337,
      "bid_volume_10": 6,
      "ask_volume_10": 3
    },
    "belts": {
      "price": 8.006,
      "open_price": 20.487,
      "last_price": 8.006,
      "moving_average": 8.006,
      "lowest_ask": 20.487,
      "high_price": 20.487,
      "low_price": 20.487,
      "volume": 0,
      "volume_prev_12": 0,
      "ask_volume_10": 2
    },
    "blades": {
      "price": 14.475,
      "last_price": 14.475,
      "moving_average": 14.475,
      "high_price": 14.475,
      "low_price": 14.475,
      "volume": 0,
      "volume_prev_12": 0
    },
    "bread": {
      "price": 2.639,
      "open_price": 2.639,
      "last_price": 2.639,
      "average_price": 2.639,
      "moving_average": 2.45,
      "highest_bid": 2.594,
      "lowest_ask": 2.639,
      "high_price": 2.639,
      "low_price": 2.639,
      "volume": 145,
      "volume_prev_12": 1806,
      "bid_volume_10": 15,
      "ask_volume_10": 9
    },
    "bricks": {
      "price": 14.451,
      "open_price": 14.451,
      "last_price": 14.451,
      "average_price": 14.451,
      "moving_average": 9.252,
      "highest_bid": 6.18,
      "high_price": 14.451,
      "low_price": 14.451,
      "volume": 2,
      "volume_prev_12": 4,
      "bid_volume_10": 1
    },
    "butter": {
      "price": 91.185,
      "open_price": 250.251,
      "last_price": 91.185,
      "moving_average": 91.185,
      "lowest_ask": 250.251,
      "high_price": 250.251,
      "low_price": 250.251,
      "volume": 0,
      "volume_prev_12": 0,
      "ask_volume_10": 2
    },
    "candles": {
      "price": 75.464,
      "open_price": 75.464,
      "last_price": 75.464,
      "moving_average": 75.464,
      "lowest_ask": 75.464,
      "high_price": 75.464,
      "low_price": 75.464,
      "volume": 0,
      "volume_prev_12": 1,
      "ask_volume_10": 1
    },
    "carting": {
      "price": 0.879,
      "open_price": 0.879,
      "last_price": 0.879,
      "average_price": 0.879,
      "moving_average": 0.573,
      "highest_bid": 0.879,
      "lowest_ask": 0.892,
      "high_price": 0.879,
      "low_price": 0.879,
      "volume": 5,
      "volume_prev_12": 236,
      "bid_volume_10": 53,
      "ask_volume_10": 10000005
    },
    "casks": {
      "price": 3.043,
      "open_price": 3.043,
      "last_price": 3.043,
      "average_price": 3.043,
      "moving_average": 3.043,
      "lowest_ask": 3.043,
      "high_price": 3.043,
      "low_price": 3.043,
      "volume": 3,
      "volume_prev_12": 36,
      "ask_volume_10": 4
    },
    "cattle": {
      "price": 35.263,
      "open_price": 102.159,
      "last_price": 35.263,
      "moving_average": 31.719,
      "lowest_ask": 102.159,
      "high_price": 102.159,
      "low_price": 102.159,
      "volume": 0,
      "volume_prev_12": 3,
      "ask_volume_10": 2
    },
    "charcoal": {
      "price": 2.23,
      "open_price": 2.23,
      "last_price": 2.23,
      "average_price": 2.23,
      "moving_average": 2.036,
      "highest_bid": 2.23,
      "lowest_ask": 2.312,
      "high_price": 2.23,
      "low_price": 2.23,
      "volume": 7,
      "volume_prev_12": 73,
      "bid_volume_10": 1,
      "ask_volume_10": 1
    },
    "cheese": {
      "price": 5.286,
      "open_price": 5.286,
      "last_price": 5.286,
      "average_price": 5.286,
      "moving_average": 5.166,
      "highest_bid": 5.286,
      "high_price": 5.286,
      "low_price": 5.286,
      "volume": 20,
      "volume_prev_12": 193,
      "bid_volume_10": 3
    },
    "clay": {
      "price": 0,
      "volume": 0,
      "volume_prev_12": 0
    },
    "cloth": {
      "price": 7.093,
      "open_price": 7.093,
      "last_price": 7.093,
      "average_price": 7.093,
      "moving_average": 7.843,
      "highest_bid": 7.093,
      "lowest_ask": 7.195,
      "high_price": 7.093,
      "low_price": 7.093,
      "volume": 10,
      "volume_prev_12": 137,
      "bid_volume_10": 5,
      "ask_volume_10": 2
    },
    "coats": {
      "price": 79.083,
      "open_price": 79.083,
      "last_price": 74.696,
      "moving_average": 74.696,
      "highest_bid": 79.083,
      "lowest_ask": 104.829,
      "high_price": 79.083,
      "low_price": 79.083,
      "volume": 0,
      "volume_prev_12": 0,
      "bid_volume_10": 1,
      "ask_volume_10": 1
    },
    "cookware": {
      "price": 18.391,
      "open_price": 18.391,
      "last_price": 18.018,
      "moving_average": 18.715,
      "highest_bid": 18.391,
      "lowest_ask": 18.814,
      "high_price": 18.391,
      "low_price": 18.391,
      "volume": 0,
      "volume_prev_12": 17,
      "bid_volume_10": 5,
      "ask_volume_10": 1
    },
    "copper ingots": {
      "price": 19.28,
      "open_price": 75.55,
      "last_price": 19.28,
      "moving_average": 19.28,
      "lowest_ask": 75.55,
      "high_price": 75.55,
      "low_price": 75.55,
      "volume": 0,
      "volume_prev_12": 0,
      "ask_volume_10": 2
    },
    "copper ore": {
      "price": 20.028,
      "last_price": 20.028,
      "moving_average": 20.028,
      "high_price": 20.028,
      "low_price": 20.028,
      "volume": 0,
      "volume_prev_12": 0
    },
    "cured fish": {
      "price": 30.765,
      "open_price": 30.765,
      "last_price": 30.765,
      "average_price": 30.765,
      "moving_average": 29.76,
      "highest_bid": 30.54,
      "lowest_ask": 30.989,
      "high_price": 30.765,
      "low_price": 30.765,
      "volume": 3,
      "volume_prev_12": 30,
      "bid_volume_10": 1,
      "ask_volume_10": 6
    },
    "cured meat": {
      "price": 19.122,
      "open_price": 19.122,
      "last_price": 19.122,
      "average_price": 19.122,
      "moving_average": 19.315,
      "lowest_ask": 23.042,
      "high_price": 19.122,
      "low_price": 19.122,
      "volume": 6,
      "volume_prev_12": 72,
      "ask_volume_10": 6
    },
    "donations": {
      "price": 1,
      "open_price": 1,
      "last_price": 1,
      "moving_average": 1,
      "lowest_ask": 1,
      "high_price": 1,
      "low_price": 1,
      "volume": 0,
      "volume_prev_12": 0,
      "ask_volume_10": 100000
    },
    "dye": {
      "price": 67.165,
      "open_price": 125.125,
      "last_price": 67.165,
      "moving_average": 67.165,
      "lowest_ask": 125.125,
      "high_price": 125.125,
      "low_price": 125.125,
      "volume": 0,
      "volume_prev_12": 0,
      "ask_volume_10": 2
    },
    "dyed cloth": {
      "price": 19.788,
      "open_price": 19.788,
      "last_price": 19.788,
      "average_price": 19.788,
      "moving_average": 19.591,
      "highest_bid": 18.693,
      "lowest_ask": 19.788,
      "high_price": 19.788,
      "low_price": 19.788,
      "volume": 1,
      "volume_prev_12": 38,
      "bid_volume_10": 6,
      "ask_volume_10": 5
    },
    "firewood": {
      "price": 11.378,
      "open_price": 11.378,
      "last_price": 11.378,
      "average_price": 11.378,
      "moving_average": 10.272,
      "highest_bid": 11.308,
      "lowest_ask": 11.378,
      "high_price": 11.378,
      "low_price": 11.378,
      "volume": 27,
      "volume_prev_12": 371,
      "bid_volume_10": 11,
      "ask_volume_10": 9
    },
    "fish": {
      "price": 4.336,
      "open_price": 4.336,
      "last_price": 4.336,
      "average_price": 4.336,
      "moving_average": 6.048,
      "highest_bid": 4.336,
      "high_price": 4.336,
      "low_price": 4.336,
      "volume": 1,
      "volume_prev_12": 6,
      "bid_volume_10": 4
    },
    "flax fibres": {
      "price": 4.16,
      "open_price": 4.16,
      "last_price": 4.16,
      "average_price": 4.16,
      "moving_average": 4.183,
      "lowest_ask": 5.134,
      "high_price": 4.16,
      "low_price": 4.16,
      "volume": 5,
      "volume_prev_12": 92,
      "ask_volume_10": 3
    },
    "flax plants": {
      "price": 2.364,
      "open_price": 2.364,
      "last_price": 2.364,
      "average_price": 2.364,
      "moving_average": 1.028,
      "highest_bid": 1.684,
      "lowest_ask": 3.333,
      "high_price": 2.364,
      "low_price": 2.364,
      "volume": 1,
      "volume_prev_12": 7,
      "bid_volume_10": 1,
      "ask_volume_10": 1
    },
    "flour": {
      "price": 32.333,
      "open_price": 31.065,
      "last_price": 32.333,
      "moving_average": 32.333,
      "highest_bid": 31.065,
      "lowest_ask": 41.179,
      "high_price": 31.065,
      "low_price": 31.065,
      "volume": 0,
      "volume_prev_12": 1,
      "bid_volume_10": 1,
      "ask_volume_10": 1
    },
    "furniture": {
      "price": 12.843,
      "open_price": 12.843,
      "last_price": 12.843,
      "average_price": 12.843,
      "moving_average": 11.438,
      "highest_bid": 11.654,
      "lowest_ask": 12.843,
      "high_price": 12.843,
      "low_price": 12.843,
      "volume": 4,
      "volume_prev_12": 40,
      "bid_volume_10": 1,
      "ask_volume_10": 3
    },
    "garments": {
      "price": 22.612,
      "open_price": 22.612,
      "last_price": 22.612,
      "average_price": 22.612,
      "moving_average": 24.499,
      "highest_bid": 22.527,
      "lowest_ask": 22.67,
      "high_price": 22.612,
      "low_price": 22.612,
      "volume": 10,
      "volume_prev_12": 114,
      "bid_volume_10": 2,
      "ask_volume_10": 7
    },
    "glass": {
      "price": 0,
      "volume": 0,
      "volume_prev_12": 0
    },
    "glassware": {
      "price": 60.168,
      "open_price": 125.684,
      "last_price": 60.168,
      "moving_average": 60.168,
      "lowest_ask": 125.684,
      "high_price": 125.684,
      "low_price": 125.684,
      "volume": 0,
      "volume_prev_12": 0,
      "ask_volume_10": 2
    },
    "gold bars": {
      "price": 1800,
      "open_price": 1652.4,
      "last_price": 1800,
      "moving_average": 1800,
      "highest_bid": 1652.4,
      "lowest_ask": 2019.599,
      "high_price": 1652.4,
      "low_price": 1652.4,
      "volume": 0,
      "volume_prev_12": 0,
      "bid_volume_10": 1,
      "ask_volume_10": 1
    },
    "gold ore": {
      "price": 321.44,
      "open_price": 431.722,
      "last_price": 321.44,
      "moving_average": 321.44,
      "lowest_ask": 431.722,
      "high_price": 431.722,
      "low_price": 431.722,
      "volume": 0,
      "volume_prev_12": 0,
      "ask_volume_10": 1
    },
    "grain": {
      "price": 2.732,
      "open_price": 2.732,
      "last_price": 2.732,
      "average_price": 2.732,
      "moving_average": 2.579,
      "highest_bid": 2.732,
      "lowest_ask": 2.739,
      "high_price": 2.732,
      "low_price": 2.732,
      "volume": 122,
      "volume_prev_12": 1611,
      "bid_volume_10": 14,
      "ask_volume_10": 43
    },
    "grindstones": {
      "price": 400,
      "open_price": 337.12,
      "last_price": 400,
      "moving_average": 400,
      "highest_bid": 337.12,
      "lowest_ask": 446.879,
      "high_price": 337.12,
      "low_price": 337.12,
      "volume": 0,
      "volume_prev_12": 0,
      "bid_volume_10": 1,
      "ask_volume_10": 1
    },
    "ham": {
      "price": 148.675,
      "open_price": 254.642,
      "last_price": 148.675,
      "moving_average": 148.675,
      "lowest_ask": 254.642,
      "high_price": 254.642,
      "low_price": 254.642,
      "volume": 0,
      "volume_prev_12": 0,
      "ask_volume_10": 2
    },
    "harnesses": {
      "price": 25.661,
      "open_price": 17.987,
      "last_price": 25.661,
      "moving_average": 26.483,
      "highest_bid": 17.987,
      "lowest_ask": 32.409,
      "high_price": 17.987,
      "low_price": 17.987,
      "volume": 0,
      "volume_prev_12": 6,
      "bid_volume_10": 1,
      "ask_volume_10": 1
    },
    "herbs": {
      "price": 63.354,
      "open_price": 63.354,
      "last_price": 21.261,
      "moving_average": 21.261,
      "highest_bid": 63.354,
      "lowest_ask": 91.166,
      "high_price": 63.354,
      "low_price": 63.354,
      "volume": 0,
      "volume_prev_12": 0,
      "bid_volume_10": 1,
      "ask_volume_10": 1
    },
    "hides": {
      "price": 8.841,
      "open_price": 8.841,
      "last_price": 8.802,
      "moving_average": 9.51,
      "highest_bid": 8.841,
      "lowest_ask": 14.693,
      "high_price": 8.841,
      "low_price": 8.841,
      "volume": 0,
      "volume_prev_12": 3,
      "bid_volume_10": 1,
      "ask_volume_10": 3
    },
    "honey": {
      "price": 2.206,
      "open_price": 6.308,
      "last_price": 2.206,
      "moving_average": 2.206,
      "lowest_ask": 6.308,
      "high_price": 6.308,
      "low_price": 6.308,
      "volume": 0,
      "volume_prev_12": 0,
      "ask_volume_10": 2
    },
    "hop beer": {
      "price": 14.584,
      "open_price": 21.584,
      "last_price": 14.584,
      "moving_average": 14.584,
      "lowest_ask": 21.584,
      "high_price": 21.584,
      "low_price": 21.584,
      "volume": 0,
      "volume_prev_12": 0,
      "ask_volume_10": 2
    },
    "iron ore": {
      "price": 3.339,
      "open_price": 3.339,
      "last_price": 3.339,
      "average_price": 3.339,
      "moving_average": 4.055,
      "high_price": 3.339,
      "low_price": 3.339,
      "volume": 9,
      "volume_prev_12": 68
    },
    "jewellery": {
      "price": 46.56,
      "open_price": 156.407,
      "last_price": 46.56,
      "moving_average": 46.56,
      "lowest_ask": 156.407,
      "high_price": 156.407,
      "low_price": 156.407,
      "volume": 0,
      "volume_prev_12": 0,
      "ask_volume_10": 2
    },
    "labour": {
      "price": 1.347,
      "open_price": 1.347,
      "last_price": 1.347,
      "average_price": 1.347,
      "moving_average": 1.281,
      "highest_bid": 1.347,
      "lowest_ask": 1.357,
      "high_price": 1.347,
      "low_price": 1.347,
      "volume": 695,
      "volume_prev_12": 9246,
      "bid_volume_10": 89,
      "ask_volume_10": 160
    },
    "lead bars": {
      "price": 15.954,
      "open_price": 16.07,
      "last_price": 15.954,
      "moving_average": 15.954,
      "lowest_ask": 16.07,
      "high_price": 16.07,
      "low_price": 16.07,
      "volume": 0,
      "volume_prev_12": 7,
      "ask_volume_10": 2
    },
    "lead ore": {
      "price": 13.027,
      "open_price": 10.951,
      "last_price": 13.027,
      "moving_average": 13.027,
      "highest_bid": 10.951,
      "high_price": 10.951,
      "low_price": 10.951,
      "volume": 0,
      "volume_prev_12": 0,
      "bid_volume_10": 1
    },
    "leather": {
      "price": 22.905,
      "open_price": 61.464,
      "last_price": 22.905,
      "moving_average": 22.905,
      "lowest_ask": 61.464,
      "high_price": 61.464,
      "low_price": 61.464,
      "volume": 0,
      "volume_prev_12": 0,
      "ask_volume_10": 2
    },
    "light armor": {
      "price": 0,
      "volume": 0,
      "volume_prev_12": 0
    },
    "limestone": {
      "price": 44.625,
      "last_price": 44.625,
      "moving_average": 44.625,
      "high_price": 44.625,
      "low_price": 44.625,
      "volume": 0,
      "volume_prev_12": 0
    },
    "lodging": {
      "price": 1.463,
      "open_price": 1.463,
      "last_price": 1.463,
      "average_price": 1.463,
      "moving_average": 1.497,
      "lowest_ask": 1.463,
      "high_price": 1.463,
      "low_price": 1.463,
      "volume": 9,
      "volume_prev_12": 114,
      "ask_volume_10": 35
    },
    "lumber": {
      "price": 14.338,
      "open_price": 0.482,
      "last_price": 14.338,
      "moving_average": 14.338,
      "lowest_ask": 0.482,
      "high_price": 0.482,
      "low_price": 0.482,
      "volume": 0,
      "volume_prev_12": 2,
      "ask_volume_10": 1
    },
    "malt": {
      "price": 10.258,
      "open_price": 10.258,
      "last_price": 10.258,
      "average_price": 10.258,
      "moving_average": 14.231,
      "lowest_ask": 10.258,
      "high_price": 10.258,
      "low_price": 10.258,
      "volume": 1,
      "volume_prev_12": 0,
      "ask_volume_10": 1
    },
    "manure": {
      "price": 0.048,
      "open_price": 0.074,
      "last_price": 0.048,
      "moving_average": 0.048,
      "lowest_ask": 0.124,
      "high_price": 0.074,
      "low_price": 0.074,
      "volume": 0,
      "volume_prev_12": 0,
      "ask_volume_10": 2
    },
    "meat": {
      "price": 1.891,
      "last_price": 1.891,
      "moving_average": 1.891,
      "high_price": 1.891,
      "low_price": 1.891,
      "volume": 0,
      "volume_prev_12": 0
    },
    "medicine": {
      "price": 158.098,
      "open_price": 208.542,
      "last_price": 158.098,
      "moving_average": 158.098,
      "lowest_ask": 208.542,
      "high_price": 208.542,
      "low_price": 208.542,
      "volume": 0,
      "volume_prev_12": 0,
      "ask_volume_10": 2
    },
    "milk": {
      "price": 4.5,
      "open_price": 4.5,
      "last_price": 1.431,
      "moving_average": 1.431,
      "highest_bid": 4.5,
      "high_price": 4.5,
      "low_price": 4.5,
      "volume": 0,
      "volume_prev_12": 10,
      "bid_volume_10": 2
    },
    "mouldboards": {
      "price": 0,
      "volume": 0,
      "volume_prev_12": 0
    },
    "nails": {
      "price": 6.641,
      "open_price": 6.641,
      "last_price": 6.641,
      "average_price": 6.641,
      "moving_average": 6.078,
      "highest_bid": 5.711,
      "lowest_ask": 6.864,
      "high_price": 6.641,
      "low_price": 6.641,
      "volume": 3,
      "volume_prev_12": 32,
      "bid_volume_10": 5,
      "ask_volume_10": 2
    },
    "nets": {
      "price": 35.502,
      "open_price": 35.502,
      "last_price": 35.502,
      "average_price": 35.502,
      "moving_average": 37.544,
      "highest_bid": 34.201,
      "lowest_ask": 37.328,
      "high_price": 35.502,
      "low_price": 35.502,
      "volume": 1,
      "volume_prev_12": 23,
      "bid_volume_10": 1,
      "ask_volume_10": 4
    },
    "ox power": {
      "price": 1.217,
      "last_price": 1.217,
      "moving_average": 1.217,
      "high_price": 1.217,
      "low_price": 1.217,
      "volume": 0,
      "volume_prev_12": 0
    },
    "pasties": {
      "price": 15.647,
      "open_price": 15.647,
      "last_price": 14.45,
      "moving_average": 14.45,
      "highest_bid": 15.647,
      "lowest_ask": 21.607,
      "high_price": 15.647,
      "low_price": 15.647,
      "volume": 0,
      "volume_prev_12": 0,
      "bid_volume_10": 1,
      "ask_volume_10": 1
    },
    "pickaxes": {
      "price": 9.537,
      "open_price": 22.244,
      "last_price": 9.537,
      "moving_average": 9.537,
      "lowest_ask": 22.244,
      "high_price": 22.244,
      "low_price": 22.244,
      "volume": 0,
      "volume_prev_12": 0,
      "ask_volume_10": 2
    },
    "pies": {
      "price": 23.343,
      "open_price": 23.343,
      "last_price": 23.343,
      "average_price": 23.343,
      "moving_average": 23.081,
      "highest_bid": 21.818,
      "lowest_ask": 23.343,
      "high_price": 23.343,
      "low_price": 23.343,
      "volume": 2,
      "volume_prev_12": 26,
      "bid_volume_10": 1,
      "ask_volume_10": 3
    },
    "ploughs": {
      "price": 71.751,
      "open_price": 181.57,
      "last_price": 71.751,
      "moving_average": 71.751,
      "lowest_ask": 181.57,
      "high_price": 181.57,
      "low_price": 181.57,
      "volume": 0,
      "volume_prev_12": 0,
      "ask_volume_10": 2
    },
    "protection": {
      "price": 8.689,
      "open_price": 8.689,
      "last_price": 8.689,
      "average_price": 8.689,
      "moving_average": 8.66,
      "highest_bid": 8.625,
      "high_price": 8.689,
      "low_price": 8.689,
      "volume": 2,
      "volume_prev_12": 24,
      "bid_volume_10": 9
    },
    "resin": {
      "price": 0,
      "volume": 0,
      "volume_prev_12": 0
    },
    "rope": {
      "price": 114.179,
      "open_price": 77.624,
      "last_price": 114.179,
      "moving_average": 114.179,
      "highest_bid": 77.624,
      "lowest_ask": 107.194,
      "high_price": 77.624,
      "low_price": 77.624,
      "volume": 0,
      "volume_prev_12": 0,
      "bid_volume_10": 1,
      "ask_volume_10": 1
    },
    "sails": {
      "price": 0,
      "volume": 0,
      "volume_prev_12": 0
    },
    "salt": {
      "price": 5.011,
      "open_price": 5.011,
      "last_price": 5.011,
      "average_price": 5.011,
      "moving_average": 5.426,
      "highest_bid": 4.777,
      "lowest_ask": 5.192,
      "high_price": 5.011,
      "low_price": 5.011,
      "volume": 5,
      "volume_prev_12": 44,
      "bid_volume_10": 2,
      "ask_volume_10": 2
    },
    "scythes": {
      "price": 0,
      "volume": 0,
      "volume_prev_12": 0
    },
    "silver bars": {
      "price": 0,
      "volume": 0,
      "volume_prev_12": 0
    },
    "slaked lime": {
      "price": 0,
      "volume": 0,
      "volume_prev_12": 0
    },
    "spirits": {
      "price": 0,
      "volume": 0,
      "volume_prev_12": 0
    },
    "steel ingots": {
      "price": 15.617,
      "open_price": 11.091,
      "last_price": 15.617,
      "moving_average": 15.617,
      "lowest_ask": 11.091,
      "high_price": 11.091,
      "low_price": 11.091,
      "volume": 0,
      "volume_prev_12": 0,
      "ask_volume_10": 1
    },
    "stockfish": {
      "price": 142.132,
      "open_price": 241.471,
      "last_price": 142.132,
      "moving_average": 142.132,
      "lowest_ask": 241.471,
      "high_price": 241.471,
      "low_price": 241.471,
      "volume": 0,
      "volume_prev_12": 0,
      "ask_volume_10": 2
    },
    "swords": {
      "price": 0,
      "volume": 0,
      "volume_prev_12": 0
    },
    "tar": {
      "price": 10.569,
      "open_price": 10.569,
      "last_price": 10.569,
      "average_price": 10.569,
      "moving_average": 12.002,
      "lowest_ask": 11.635,
      "high_price": 10.569,
      "low_price": 10.569,
      "volume": 1,
      "volume_prev_12": 4,
      "ask_volume_10": 2
    },
    "thread": {
      "price": 4.734,
      "open_price": 4.734,
      "last_price": 4.734,
      "average_price": 4.734,
      "moving_average": 3.791,
      "lowest_ask": 4.768,
      "high_price": 4.734,
      "low_price": 4.734,
      "volume": 10,
      "volume_prev_12": 67,
      "ask_volume_10": 3
    },
    "tiles": {
      "price": 7.603,
      "open_price": 7.603,
      "last_price": 7.603,
      "average_price": 7.603,
      "moving_average": 4.483,
      "highest_bid": 7.603,
      "high_price": 7.603,
      "low_price": 7.603,
      "volume": 1,
      "volume_prev_12": 11,
      "bid_volume_10": 3
    },
    "timber": {
      "price": 8.016,
      "open_price": 8.016,
      "last_price": 8.016,
      "average_price": 8.016,
      "moving_average": 8.276,
      "highest_bid": 7.583,
      "lowest_ask": 8.016,
      "high_price": 8.016,
      "low_price": 8.016,
      "volume": 16,
      "volume_prev_12": 171,
      "bid_volume_10": 1,
      "ask_volume_10": 10
    },
    "tools": {
      "price": 4.82,
      "open_price": 4.82,
      "last_price": 4.82,
      "average_price": 4.82,
      "moving_average": 5.16,
      "highest_bid": 4.394,
      "lowest_ask": 4.82,
      "high_price": 4.82,
      "low_price": 4.82,
      "volume": 9,
      "volume_prev_12": 92,
      "bid_volume_10": 1,
      "ask_volume_10": 4
    },
    "wax": {
      "price": 29.251,
      "open_price": 60.367,
      "last_price": 29.251,
      "moving_average": 29.251,
      "lowest_ask": 60.367,
      "high_price": 60.367,
      "low_price": 60.367,
      "volume": 0,
      "volume_prev_12": 0,
      "ask_volume_10": 2
    },
    "wheels": {
      "price": 24.841,
      "open_price": 50.927,
      "last_price": 24.841,
      "moving_average": 24.841,
      "lowest_ask": 50.927,
      "high_price": 50.927,
      "low_price": 50.927,
      "volume": 0,
      "volume_prev_12": 0,
      "ask_volume_10": 2
    },
    "windows": {
      "price": 0,
      "volume": 0,
      "volume_prev_12": 0
    },
    "wine": {
      "price": 8.624,
      "open_price": 8.624,
      "last_price": 8.624,
      "moving_average": 8.624,
      "highest_bid": 8.624,
      "lowest_ask": 10.975,
      "high_price": 8.624,
      "low_price": 8.624,
      "volume": 0,
      "volume_prev_12": 1,
      "bid_volume_10": 1,
      "ask_volume_10": 1
    },
    "wool": {
      "price": 7.732,
      "open_price": 7.732,
      "last_price": 7.732,
      "average_price": 7.732,
      "moving_average": 6.422,
      "highest_bid": 7.724,
      "lowest_ask": 7.995,
      "high_price": 7.732,
      "low_price": 7.732,
      "volume": 14,
      "volume_prev_12": 158,
      "bid_volume_10": 7,
      "ask_volume_10": 6
    },
    "wrought iron": {
      "price": 11.12,
      "open_price": 11.12,
      "last_price": 11.12,
      "average_price": 11.12,
      "moving_average": 12.099,
      "highest_bid": 11.087,
      "lowest_ask": 11.247,
      "high_price": 11.12,
      "low_price": 11.12,
      "volume": 9,
      "volume_prev_12": 82,
      "bid_volume_10": 8,
      "ask_volume_10": 1
    },
    "yarn": {
      "price": 2.267,
      "open_price": 2.267,
      "last_price": 2.267,
      "average_price": 2.267,
      "moving_average": 4.138,
      "lowest_ask": 2.267,
      "high_price": 2.267,
      "low_price": 2.267,
      "volume": 8,
      "volume_prev_12": 73,
      "ask_volume_10": 4
    }
  },
  "_ts": 1718903409306447
}